troncos/__init__.py
troncos/contrib/__init__.py
troncos/contrib/asgi/__init__.py
troncos/contrib/asgi/logging/__init__.py
troncos/contrib/asgi/logging/middleware.py
troncos/contrib/celery/__init__.py
troncos/contrib/celery/logging/__init__.py
troncos/contrib/celery/logging/signals.py
troncos/contrib/django/__init__.py
troncos/contrib/django/logging/__init__.py
troncos/contrib/django/logging/middleware.py
troncos/contrib/logging/__init__.py
troncos/contrib/logging/tools/__init__.py
troncos/contrib/structlog/__init__.py
troncos/contrib/structlog/processors.py
troncos/py.typed
troncos/tracing/__init__.py
troncos/tracing/_exporter.py
troncos/tracing/_otel.py
troncos/tracing/_span.py
troncos/tracing/_writer.py
troncos/tracing/decorators.py
troncos-8.0.1.dist-info/LICENSE
troncos-8.0.1.dist-info/METADATA
troncos-8.0.1.dist-info/WHEEL
troncos-8.0.1.dist-info/RECORD
