Metadata-Version: 2.3
Name: troncos
Version: 8.0.1
Summary: Collection of Python logging and tracing tools
License: MIT
Keywords: logs,traces,opentelemetry
Author: Guðmundur Björn Birkisson
Author-email: gudmundur.birkisson@oda.com
Requires-Python: >=3.11,<3.15
Classifier: License :: OSI Approved :: MIT License
Classifier: Programming Language :: Python :: 3
Classifier: Programming Language :: Python :: 3.11
Classifier: Programming Language :: Python :: 3.12
Classifier: Programming Language :: Python :: 3.13
Provides-Extra: grpc
Provides-Extra: sentry
Requires-Dist: ddtrace (==4.1.2)
Requires-Dist: opentelemetry-exporter-otlp-proto-grpc (>=1.19,<2) ; extra == "grpc"
Requires-Dist: opentelemetry-exporter-otlp-proto-http (>=1.19,<2)
Requires-Dist: opentelemetry-sdk (>=1.19,<2)
Requires-Dist: python-ipware (>=2,<4)
Requires-Dist: structlog-sentry (>=2.0.0,<3) ; extra == "sentry"
Project-URL: Documentation, https://github.com/kolonialno/troncos
Project-URL: Homepage, https://github.com/kolonialno/troncos
Project-URL: Repository, https://github.com/kolonialno/troncos
